{"username": "radityadika", "words": {"film": 277, "gue": 219, "hangout": 182, "baru": 119, "dan": 114, "bang": 112, "dari": 94, "video": 87, "yang": 85, "mau": 74, "jam": 53, "apa": 49, "review": 42, "cinema": 42, "pal": 34, "kalo": 33, "kali": 33, "orang": 33, "squishy": 24, "part": 23, "mana": 23, "tau": 20, "overwatch": 20, "trailer": 19, "bakal": 18, "shoot": 18, "main": 18, "rame": 16, "aku": 15, "studio": 14, "dika": 12, "sore": 11, "kayak": 11, "nice": 11, "parah": 10, "horror": 10, "stream": 10, "weekend": 10, "hotel": 10, "lama": 9, "bangkok": 9, "scene": 9, "saya": 9, "demi": 9, "acara": 8, "live": 8, "meeting": 8, "game": 8, "werewolf": 8, "sma": 8, "festival": 8, "kopi": 8, "time": 7, "teman": 7, "kiri": 7, "action": 7, "day": 7, "thanks": 7, "battleground": 7, "movie": 7, "masa": 7, "share": 7, "pun": 6, "naik": 6, "dah": 6, "topi": 6, "premiere": 6, "city": 6, "taun": 6, "plaza": 6, "net": 6, "deg": 6, "see": 5, "shooting": 5, "tragedy": 5, "come": 5, "bali": 5, "valerian": 5, "today": 5, "yah": 5, "band": 5, "wow": 5, "jaman": 5, "post": 5, "titi": 5, "wah": 5, "fallen": 5, "channel": 4, "twitter": 4, "badan": 4, "pop": 4, "kalian": 4, "draft": 4, "thriller": 4, "poster": 4, "overdrive": 4, "lain": 4, "thousand": 4, "set": 4, "comedy": 4, "jawab": 4, "ma": 4, "gong": 4, "dong": 4, "meet": 4, "pink": 4, "rapper": 4, "cast": 4, "single": 4, "lunch": 4, "mall": 4, "coconut": 4, "delight": 4, "season": 3, "caption": 3, "thank": 3, "show": 3, "tampan": 3, "gym": 3, "creative": 3, "writer": 3, "path": 3, "exile": 3, "test": 3, "drive": 3, "let": 3, "romance": 3, "arena": 3, "kan": 3, "motor": 3, "ria": 3, "happy": 3, "birthday": 3, "land": 3, "fidget": 3, "spinner": 3, "baby": 3, "canon": 3, "diem": 3, "money": 3, "box": 3, "person": 3, "year": 3, "tape": 3, "unlocked": 3, "diet": 3, "medium": 3, "award": 3, "transit": 3, "carpet": 3, "dim": 3, "enjoy": 3, "party": 3, "make": 3, "blue": 3, "bong": 3, "cover": 3, "add": 3, "climb": 3, "challenge": 3, "line": 3, "bola": 3, "fix": 3, "paling": 3, "amin": 3, "sell": 3, "rasa": 3, "greet": 3, "morning": 3, "subscribe": 2, "stand": 2, "next": 2, "fun": 2, "teaser": 2, "bank": 2, "league": 2, "dark": 2, "ala": 2, "navy": 2, "say": 2, "house": 2, "koala": 2, "hall": 2, "repot": 2, "episode": 2, "battle": 2, "rap": 2, "yak": 2, "tanker": 2, "spider": 2, "man": 2, "design": 2, "bake": 2, "sound": 2, "pes": 2, "draw": 2, "life": 2, "support": 2, "lie": 2, "travel": 2, "woohoo": 2, "agar": 2, "family": 2, "news": 2, "error": 2, "boom": 2, "rog": 2, "provider": 2, "stage": 2, "raise": 2, "soon": 2, "zaman": 2, "innovative": 2, "mark": 2, "call": 2, "treadmill": 2, "pisang": 2, "office": 2, "project": 2, "love": 2, "producer": 2, "bela": 2, "vote": 2, "tweet": 2, "world": 2, "intellectual": 2, "property": 2, "ham": 2, "interview": 2, "sangar": 2, "miss": 2, "red": 2, "session": 2, "coming": 2, "late": 2, "one": 2, "sweet": 2, "berat": 2, "event": 2, "camera": 2, "legend": 2, "frame": 2, "healer": 2, "gratis": 2, "maestro": 2, "potong": 2, "brutal": 2, "kind": 2, "nais": 2, "drama": 2, "target": 2, "kaka": 2, "ritual": 2, "quiz": 2, "enam": 2, "super": 2, "square": 2, "spoiler": 2, "gara": 2, "mention": 2, "uncle": 2, "gala": 2, "persis": 2, "academy": 2, "giveaway": 1, "batik": 1, "well": 1, "deserve": 1, "papa": 1, "remote": 1, "perform": 1, "performance": 1, "great": 1, "storytelling": 1, "ride": 1, "cash": 1, "duet": 1, "bird": 1, "sept": 1, "welcome": 1, "club": 1, "tutorial": 1, "ketogenic": 1, "yoghurt": 1, "fat": 1, "chocolate": 1, "humor": 1, "gan": 1, "do": 1, "glow": 1, "gin": 1, "radio": 1, "salon": 1, "model": 1, "rupiah": 1, "han": 1, "poe": 1, "storyteller": 1, "hiro": 1, "sam": 1, "novel": 1, "dog": 1, "pia": 1, "cod": 1, "mining": 1, "reply": 1, "young": 1, "fast": 1, "furious": 1, "hot": 1, "babe": 1, "eta": 1, "paladin": 1, "tank": 1, "valor": 1, "formula": 1, "diver": 1, "tang": 1, "buckle": 1, "clasp": 1, "story": 1, "char": 1, "brown": 1, "monster": 1, "marten": 1, "nickname": 1, "duty": 1, "school": 1, "poll": 1, "cap": 1, "cup": 1, "carry": 1, "popcorn": 1, "mania": 1, "shop": 1, "haul": 1, "chicken": 1, "rice": 1, "star": 1, "minus": 1, "dad": 1, "snoopy": 1, "duel": 1, "tekken": 1, "friend": 1, "mind": 1, "read": 1, "boomerang": 1, "master": 1, "yes": 1, "holt": 1, "groot": 1, "dessert": 1, "plain": 1, "berry": 1, "lentil": 1, "soup": 1, "render": 1, "sirloin": 1, "steak": 1, "butter": 1, "rip": 1, "know": 1, "slime": 1, "rain": 1, "trio": 1, "speaker": 1, "phone": 1, "yakin": 1, "forum": 1, "influencer": 1, "marketing": 1, "sorry": 1, "core": 1, "ram": 1, "display": 1, "alarm": 1, "movement": 1, "cheat": 1, "luna": 1, "maya": 1, "towel": 1, "merry": 1, "tua": 1, "marinade": 1, "doll": 1, "critical": 1, "eleven": 1, "trapezius": 1, "pillow": 1, "talk": 1, "rig": 1, "wolverine": 1, "sate": 1, "unlock": 1, "repace": 1, "era": 1, "senam": 1, "influential": 1, "month": 1, "request": 1, "mending": 1, "zombie": 1, "entertainer": 1, "food": 1, "forget": 1, "try": 1, "choice": 1, "hasan": 1, "landing": 1, "subscriber": 1, "drummer": 1, "check": 1, "tuan": 1, "abu": 1, "robot": 1, "situation": 1, "idol": 1, "program": 1, "car": 1, "free": 1, "china": 1, "ajar": 1, "topic": 1, "leader": 1, "pst": 1, "afternoon": 1, "write": 1, "join": 1, "epicentrum": 1, "boarding": 1, "klip": 1, "centrum": 1, "slide": 1, "pack": 1, "platinum": 1, "player": 1, "unknown": 1, "trauma": 1, "sun": 1, "tar": 1, "steam": 1, "barbershop": 1, "papaya": 1, "rambutan": 1, "mellow": 1, "entertain": 1, "people": 1, "night": 1, "snack": 1, "new": 1, "chef": 1, "randy": 1, "raya": 1, "silver": 1, "rank": 1, "helium": 1, "twit": 1, "shampoo": 1, "raja": 1, "look": 1, "wrap": 1, "almost": 1, "bit": 1, "supper": 1, "neon": 1, "piano": 1, "always": 1, "subway": 1, "feast": 1, "report": 1, "coffee": 1, "pudding": 1, "valentine": 1, "survey": 1, "lee": 1, "pose": 1, "heart": 1, "goblin": 1, "halo": 1, "beauty": 1, "prince": 1, "friendship": 1, "realm": 1, "reborn": 1, "gorilla": 1, "cat": 1, "monitor": 1, "kyle": 1, "gif": 1, "reaction": 1, "polo": 1, "dream": 1, "foolish": 1, "seem": 1, "rutin": 1, "hut": 1, "hah": 1, "corn": 1, "liar": 1, "space": 1, "grey": 1, "colback": 1, "translate": 1, "strategi": 1, "market": 1, "pedes": 1, "feel": 1, "salma": 1, "dinner": 1, "skin": 1, "hero": 1, "alfa": 1, "week": 1, "ultra": 1, "prime": 1, "eddo": 1, "book": 1, "tag": 1, "para": 1, "tour": 1, "midnight": 1, "format": 1, "shirt": 1, "dit": 1, "theater": 1, "serin": 1, "twist": 1, "poke": 1, "offbeat": 1, "nasi": 1, "success": 1, "empire": 1, "sold": 1, "link": 1, "metropolis": 1, "bat": 1, "solo": 1, "pontianak": 1, "ade": 1, "hay": 1, "full": 1, "prill": 1, "genre": 1, "gore": 1, "shi": 1, "job": 1, "watch": 1, "pattern": 1, "zee": 1, "lot": 1, "think": 1, "vino": 1, "blend": 1, "credit": 1, "ending": 1, "nan": 1, "alif": 1, "gabby": 1, "air": 1, "confirmed": 1, "delay": 1, "gram": 1, "kuru": 1, "stress": 1, "blitz": 1, "get": 1, "stop": 1, "sari": 1, "premier": 1, "struggle": 1, "level": 1, "back": 1, "crew": 1, "lock": 1, "preview": 1, "batman": 1, "stalk": 1, "hey": 1, "prize": 1, "sincere": 1, "elephant": 1, "karaoke": 1, "hammer": 1, "woy": 1, "pipi": 1, "chill": 1, "modal": 1, "jazz": 1, "deadline": 1, "slow": 1, "gerah": 1, "spicy": 1, "salmon": 1, "roll": 1, "body": 1, "original": 1, "power": 1, "point": 1, "ens": 1, "couple": 1, "mon": 1, "kusam": 1}, "emojis": {}, "interests": {"sangar": 1.0, "ketogenic": 1.0, "paladin": 1.0, "trapezius": 1.0, "repace": 1.0, "rambutan": 1.0, "colback": 1.0, "pedes": 1.0, "prill": 1.0, "kusam": 1.0, "hangout": 0.7811158798283262, "taun": 0.75, "dika": 0.6666666666666666, "nais": 0.6666666666666666, "gue": 0.5887096774193549, "squishy": 0.5714285714285714, "overdrive": 0.5714285714285714, "werewolf": 0.5333333333333333, "lentil": 0.5, "sirloin": 0.5, "serin": 0.5, "overwatch": 0.43478260869565216, "pes": 0.4, "parah": 0.35714285714285715, "kiri": 0.35, "tampan": 0.3333333333333333, "fidget": 0.3333333333333333, "marinade": 0.3333333333333333, "influential": 0.3333333333333333, "alfa": 0.3333333333333333, "eddo": 0.3333333333333333, "gerah": 0.3333333333333333, "topi": 0.3157894736842105, "yoghurt": 0.25, "ajar": 0.25, "centrum": 0.25, "titi": 0.23809523809523808, "bang": 0.2318840579710145, "rame": 0.21052631578947367, "dah": 0.20689655172413793, "deg": 0.20689655172413793, "battleground": 0.2, "unlocked": 0.2, "marten": 0.2, "papaya": 0.2, "alif": 0.2, "valerian": 0.18518518518518517, "intellectual": 0.18181818181818182, "repot": 0.16666666666666666, "potong": 0.16666666666666666, "persis": 0.16666666666666666, "hiro": 0.16666666666666666, "senam": 0.16666666666666666, "woy": 0.16666666666666666, "pipi": 0.16666666666666666, "kayak": 0.16417910447761194, "exile": 0.14285714285714285, "pisang": 0.14285714285714285, "foolish": 0.14285714285714285, "offbeat": 0.14285714285714285, "diem": 0.13636363636363635, "tekken": 0.125, "canon": 0.12, "kalo": 0.11827956989247312, "fallen": 0.1111111111111111, "eta": 0.1111111111111111, "barbershop": 0.1111111111111111, "paling": 0.10344827586206896, "sma": 0.10126582278481013, "baru": 0.10076206604572396, "epicentrum": 0.1, "metropolis": 0.1, "kuru": 0.1, "jaman": 0.09615384615384616, "innovative": 0.09090909090909091, "helium": 0.09090909090909091, "tau": 0.08888888888888889, "koala": 0.08333333333333333, "mending": 0.08333333333333333, "bong": 0.08108108108108109, "enam": 0.08, "kali": 0.07951807228915662, "mau": 0.07863974495217853, "kopi": 0.0761904761904762, "gong": 0.07407407407407407, "bakal": 0.07317073170731707, "critical": 0.07142857142857142, "mellow": 0.07142857142857142, "pal": 0.06882591093117409, "mana": 0.06784660766961652, "dim": 0.06666666666666667, "ritual": 0.06666666666666667, "clasp": 0.06666666666666667, "pontianak": 0.06666666666666667, "naik": 0.06521739130434782, "treadmill": 0.06451612903225806, "dong": 0.06060606060606061, "subscriber": 0.058823529411764705, "rutin": 0.058823529411764705, "rog": 0.05714285714285714, "bangkok": 0.055900621118012424, "coconut": 0.05555555555555555, "groot": 0.05555555555555555, "sate": 0.05555555555555555, "hah": 0.05555555555555555, "yah": 0.050505050505050504, "film": 0.04872471416007036, "sore": 0.048458149779735685, "nasi": 0.047619047619047616, "boomerang": 0.045454545454545456, "main": 0.044444444444444446, "strategi": 0.043478260869565216, "kalian": 0.043010752688172046, "healer": 0.0425531914893617, "spinner": 0.04225352112676056, "badan": 0.042105263157894736, "gara": 0.041666666666666664, "snoopy": 0.04, "supper": 0.04, "transit": 0.039473684210526314, "holt": 0.038461538461538464, "boarding": 0.038461538461538464, "gabby": 0.038461538461538464, "sincere": 0.038461538461538464, "modal": 0.038461538461538464, "apa": 0.03775038520801233, "sari": 0.037037037037037035, "dari": 0.03556564510026485, "jawab": 0.03508771929824561, "blitz": 0.034482758620689655, "diet": 0.033707865168539325, "review": 0.03365384615384615, "pudding": 0.03333333333333333, "acara": 0.03278688524590164, "horror": 0.03257328990228013, "brutal": 0.03225806451612903, "poke": 0.03225806451612903, "drummer": 0.03125, "tuan": 0.03125, "shi": 0.03125, "gore": 0.030303030303030304, "salmon": 0.030303030303030304, "jam": 0.030285714285714287, "tang": 0.029411764705882353, "plaza": 0.02926829268292683, "poe": 0.02857142857142857, "twit": 0.027777777777777776, "lama": 0.02601156069364162, "net": 0.02575107296137339, "tanker": 0.02564102564102564, "char": 0.02564102564102564, "thousand": 0.025477707006369428, "cinema": 0.025347012673506336, "reborn": 0.024390243902439025, "cod": 0.023809523809523808, "tar": 0.023809523809523808, "thriller": 0.023391812865497075, "pia": 0.023255813953488372, "rig": 0.023255813953488372, "klip": 0.023255813953488372, "gorilla": 0.022222222222222223, "stalk": 0.022222222222222223, "orang": 0.021739130434782608, "demi": 0.021634615384615384, "storyteller": 0.02127659574468085, "wah": 0.020833333333333332, "remote": 0.020833333333333332, "bela": 0.02040816326530612, "steak": 0.02040816326530612, "unknown": 0.02040816326530612, "nickname": 0.02, "eleven": 0.02, "goblin": 0.0196078431372549, "bali": 0.019455252918287938, "mania": 0.019230769230769232, "pun": 0.018691588785046728, "berat": 0.01834862385321101, "mining": 0.01818181818181818, "duel": 0.01818181818181818, "dessert": 0.01818181818181818, "hasan": 0.01818181818181818, "popcorn": 0.017857142857142856, "nan": 0.017857142857142856, "rapper": 0.017167381974248927, "kaka": 0.017094017094017096, "minus": 0.01694915254237288, "motor": 0.016666666666666666, "towel": 0.016666666666666666, "shampoo": 0.016666666666666666, "ens": 0.016666666666666666, "ending": 0.01639344262295082, "translate": 0.016129032258064516, "vino": 0.016129032258064516, "gan": 0.015873015873015872, "yakin": 0.015873015873015872, "tragedy": 0.015625, "tutorial": 0.015625, "rupiah": 0.015625, "randy": 0.015625, "render": 0.015384615384615385, "draft": 0.015151515151515152, "yak": 0.015151515151515152, "provider": 0.015151515151515152, "diver": 0.015151515151515152, "gin": 0.014925373134328358, "zaman": 0.014705882352941176, "woohoo": 0.014598540145985401, "teman": 0.014583333333333334, "tape": 0.014563106796116505, "bake": 0.014388489208633094, "aku": 0.014340344168260038, "gram": 0.014285714285714285, "bola": 0.013888888888888888, "corn": 0.013888888888888888, "plain": 0.0136986301369863, "steam": 0.0136986301369863, "masa": 0.013565891472868217, "dan": 0.013348946135831381, "batik": 0.013333333333333334, "influencer": 0.013157894736842105, "pattern": 0.013157894736842105, "storytelling": 0.012987012987012988, "wolverine": 0.012987012987012988, "salon": 0.01282051282051282, "ade": 0.01282051282051282, "property": 0.012578616352201259, "ala": 0.012269938650306749, "spoiler": 0.012195121951219513, "dit": 0.012195121951219513, "studio": 0.01217391304347826, "zombie": 0.012048192771084338, "spicy": 0.012048192771084338, "polo": 0.011764705882352941, "climb": 0.01171875, "scene": 0.011658031088082901, "mall": 0.011627906976744186, "nice": 0.011470281543274244, "pillow": 0.011235955056179775, "feast": 0.010869565217391304, "creative": 0.010752688172043012, "elephant": 0.010638297872340425, "hammer": 0.010638297872340425, "amin": 0.010526315789473684, "shooting": 0.010482180293501049, "hotel": 0.010438413361169102, "haul": 0.010416666666666666, "confirmed": 0.010309278350515464, "zee": 0.010101010101010102, "greet": 0.010067114093959731, "furious": 0.01, "salma": 0.01, "romance": 0.009966777408637873, "hut": 0.009900990099009901, "gratis": 0.009708737864077669, "monitor": 0.009708737864077669, "delight": 0.009685230024213076, "frame": 0.00966183574879227, "berry": 0.009615384615384616, "rasa": 0.00949367088607595, "buckle": 0.009345794392523364, "entertainer": 0.009345794392523364, "yang": 0.009120171673819743, "maestro": 0.009009009009009009, "lain": 0.008888888888888889, "format": 0.008849557522123894, "sold": 0.008771929824561403, "liar": 0.008695652173913044, "fat": 0.008403361344537815, "soup": 0.008264462809917356, "ham": 0.00823045267489712, "blend": 0.00819672131147541, "subway": 0.008, "genre": 0.007874015748031496, "navy": 0.007662835249042145, "marketing": 0.007518796992481203, "raja": 0.007518796992481203, "lunch": 0.0074211502782931356, "halo": 0.007352941176470588, "trauma": 0.007194244604316547, "late": 0.007168458781362007, "slime": 0.0070921985815602835, "valor": 0.007042253521126761, "neon": 0.006944444444444444, "butter": 0.006896551724137931, "trailer": 0.00680759584378359, "uncle": 0.006557377049180328, "poster": 0.006546644844517185, "spider": 0.006535947712418301, "video": 0.006502242152466368, "novel": 0.006329113924050633, "grey": 0.006289308176100629, "piano": 0.006172839506172839, "gym": 0.006147540983606557, "ultra": 0.006134969325153374, "tua": 0.006097560975609756, "raya": 0.005988023952095809, "shoot": 0.0059622391520370984, "rice": 0.005952380952380952, "kyle": 0.005917159763313609, "realm": 0.005813953488372093, "cheat": 0.0056179775280898875, "festival": 0.005598320503848845, "doll": 0.0055248618784530384, "writer": 0.005494505494505495, "topic": 0.005405405405405406, "gala": 0.005376344086021506, "rank": 0.005376344086021506, "trio": 0.005319148936170213, "mention": 0.005305039787798408, "karaoke": 0.005291005291005291, "duet": 0.005263157894736842, "jazz": 0.005235602094240838, "error": 0.005208333333333333, "subscribe": 0.00516795865633075, "quiz": 0.00516795865633075, "formula": 0.00510204081632653, "producer": 0.005063291139240506, "carpet": 0.00505902192242833, "entertain": 0.004975124378109453, "rap": 0.0049382716049382715, "path": 0.0049261083743842365, "landing": 0.0049261083743842365, "caption": 0.004893964110929853, "snack": 0.004878048780487805, "survey": 0.0048543689320388345, "band": 0.004835589941972921, "maya": 0.004807692307692308, "tank": 0.004784688995215311, "pink": 0.004739336492890996, "boom": 0.004672897196261682, "alarm": 0.004651162790697674, "arena": 0.0046439628482972135, "empire": 0.0045871559633027525, "original": 0.0045662100456621, "kan": 0.004392386530014641, "slide": 0.004347826086956522, "meeting": 0.0042643923240938165, "part": 0.004146385433567695, "premiere": 0.004103967168262654, "saya": 0.00405222872579919, "dark": 0.004016064257028112, "comedy": 0.003992015968063872, "agar": 0.0038240917782026767, "soon": 0.003816793893129771, "single": 0.0038131553860819827, "slow": 0.0038022813688212928, "pose": 0.0037735849056603774, "stress": 0.0037735849056603774, "platinum": 0.0036900369003690036, "giveaway": 0.0036496350364963502, "robot": 0.0036101083032490976, "glow": 0.0035971223021582736, "twist": 0.0034965034965034965, "stream": 0.003484320557491289, "sweet": 0.003436426116838488, "papa": 0.003205128205128205, "chef": 0.003205128205128205, "fix": 0.003188097768331562, "core": 0.0031847133757961785, "unlock": 0.0031446540880503146, "silver": 0.0031446540880503146, "gif": 0.003134796238244514, "square": 0.003048780487804878, "humor": 0.003003003003003003, "drama": 0.0029985007496251873, "academy": 0.0029850746268656717, "chocolate": 0.0029585798816568047, "monster": 0.0029069767441860465, "idol": 0.002840909090909091, "cast": 0.002803083391730904, "babe": 0.002793296089385475, "chicken": 0.0027548209366391185, "delay": 0.0027472527472527475, "blue": 0.0027347310847766638, "box": 0.00273224043715847, "theater": 0.00273224043715847, "speaker": 0.0027100271002710027, "teaser": 0.0026666666666666666, "camera": 0.00258732212160414, "action": 0.0025830258302583027, "deadline": 0.002531645569620253, "bank": 0.002509410288582183, "bird": 0.0025, "weekend": 0.002473410833539451, "sam": 0.0024390243902439024, "almost": 0.0024330900243309003, "chill": 0.0024330900243309003, "target": 0.002430133657351154, "channel": 0.0024024024024024023, "draw": 0.002386634844868735, "hall": 0.002380952380952381, "cash": 0.002369668246445498, "ram": 0.002352941176470588, "abu": 0.002336448598130841, "fast": 0.002325581395348837, "luna": 0.00228310502283105, "duty": 0.0022624434389140274, "valentine": 0.0022371364653243847, "ria": 0.0021660649819494585, "sound": 0.0021598272138228943, "coming": 0.0021551724137931034, "display": 0.0021141649048625794, "seem": 0.0020833333333333333, "pop": 0.0020242914979757085, "drive": 0.001985440105890139, "forum": 0.001949317738791423, "next": 0.001869158878504673, "sept": 0.0018587360594795538, "premier": 0.0018587360594795538, "cap": 0.0018552875695732839, "sell": 0.001829268292682927, "friendship": 0.0018148820326678765, "movie": 0.0017985611510791368, "award": 0.0017953321364452424, "master": 0.0017761989342806395, "skin": 0.0017761989342806395, "land": 0.001756440281030445, "preview": 0.0017482517482517483, "lie": 0.0016849199663016006, "brown": 0.0016806722689075631, "merry": 0.001658374792703151, "bat": 0.001652892561983471, "young": 0.0016420361247947454, "credit": 0.0016366612111292963, "reaction": 0.0016233766233766235, "lee": 0.001607717041800643, "wow": 0.0015969338869370809, "ma": 0.0015942606616181746, "challenge": 0.001571503404924044, "afternoon": 0.0015432098765432098, "add": 0.001534526854219949, "reply": 0.0015313935681470138, "travel": 0.0014992503748125937, "wrap": 0.0014903129657228018, "struggle": 0.0014705882352941176, "design": 0.0014695077149155032, "battle": 0.001467351430667645, "share": 0.001466582861931699, "pack": 0.0014577259475218659, "project": 0.0014524328249818446, "prize": 0.001451378809869376, "market": 0.001445086705202312, "request": 0.0014326647564469914, "midnight": 0.0014285714285714286, "rain": 0.00141643059490085, "cat": 0.0013812154696132596, "coffee": 0.001379310344827586, "city": 0.0013413816230717639, "situation": 0.001326259946949602, "han": 0.0013123359580052493, "line": 0.0013043478260869566, "session": 0.0012706480304955528, "prince": 0.0012391573729863693, "poll": 0.0012376237623762376, "batman": 0.0012330456226880395, "red": 0.0012300123001230013, "carry": 0.0012091898428053204, "pst": 0.0011961722488038277, "rip": 0.001177856301531213, "lock": 0.001145475372279496, "cover": 0.0011419870574800152, "league": 0.0011370096645821489, "movement": 0.0011325028312570782, "raise": 0.0011248593925759281, "money": 0.001119402985074627, "office": 0.0011179429849077697, "mark": 0.0011160714285714285, "person": 0.0011115227862171174, "mon": 0.0011098779134295228, "post": 0.0011079104808331486, "medium": 0.0010905125408942203, "model": 0.0010834236186348862, "hot": 0.0010799136069114472, "tag": 0.0010799136069114472, "ride": 0.001034126163391934, "baby": 0.001029512697323267, "dinner": 0.000984251968503937, "roll": 0.0009784735812133072, "choice": 0.000968054211035818, "sun": 0.0009293680297397769, "game": 0.0009053870529651426, "perform": 0.0008976660682226212, "event": 0.0008928571428571428, "hero": 0.0008904719501335708, "radio": 0.0008695652173913044, "enjoy": 0.0008670520231213873, "test": 0.0008505812305075135, "super": 0.0008227067050596463, "shirt": 0.0008130081300813008, "set": 0.0008107012565869477, "couple": 0.0008071025020177562, "dad": 0.0008051529790660225, "interview": 0.0007980845969672786, "prime": 0.0007974481658692185, "crew": 0.0007936507936507937, "kind": 0.0007846214201647705, "program": 0.000774593338497289, "solo": 0.000741839762611276, "bit": 0.0007304601899196494, "body": 0.0007183908045977011, "hay": 0.0006958942240779402, "twitter": 0.0006817794443497528, "success": 0.0006738544474393531, "car": 0.0006706908115358819, "deserve": 0.0006613756613756613, "stage": 0.0006482982171799027, "always": 0.000646830530401035, "legend": 0.000643915003219575, "morning": 0.0006417112299465241, "party": 0.0006225357958082589, "level": 0.0006199628022318661, "meet": 0.0006128389765589091, "beauty": 0.000612369871402327, "stand": 0.0006101281269066504, "leader": 0.0006064281382656155, "free": 0.0006006006006006006, "full": 0.0005750431282346176, "live": 0.0005714285714285715, "player": 0.0005595970900951316, "one": 0.0005538631957906397, "era": 0.0005537098560354374, "phone": 0.0005467468562055768, "sorry": 0.0005431830526887561, "episode": 0.0005257623554153522, "food": 0.0005154639175257732, "dog": 0.0005027652086475615, "cup": 0.0004928536224741252, "club": 0.0004807692307692308, "mind": 0.00047938638542665386, "call": 0.0004706989879971758, "season": 0.0004540638716512789, "point": 0.00045045045045045046, "thanks": 0.0004419470926194836, "air": 0.00043196544276457883, "well": 0.0004297378599054577, "job": 0.00042753313381787086, "happy": 0.00040005334044539273, "miss": 0.0003977724741447892, "dream": 0.0003946329913180742, "month": 0.00039416633819471815, "tweet": 0.000390015600624025, "house": 0.0003862495171881035, "welcome": 0.0003843197540353574, "fun": 0.00038218994840435696, "forget": 0.00037893141341417203, "report": 0.00036927621861152144, "write": 0.00036469730123997083, "news": 0.00035192679922576106, "link": 0.00034614053305642093, "school": 0.00034578146611341634, "space": 0.00034164673727365904, "birthday": 0.00033101621979476995, "performance": 0.0003240440699935191, "back": 0.0003224766204450177, "vote": 0.000304228780042592, "shop": 0.00029824038174768865, "china": 0.0002818489289740699, "family": 0.0002815711671124877, "hey": 0.00026595744680851064, "time": 0.00026121352339726845, "star": 0.0002512562814070352, "yes": 0.0002484472049689441, "book": 0.0002457606291472106, "day": 0.0002442684160937991, "power": 0.000241196333815726, "come": 0.0002381746296384509, "let": 0.00023464998044583498, "man": 0.00023435669088352472, "year": 0.00023315458148752622, "great": 0.0002221235006663705, "support": 0.00022190169754798624, "friend": 0.00022011886418666079, "tour": 0.0002149151085321298, "heart": 0.00021473051320592657, "today": 0.00020865500980678546, "stop": 0.00020798668885191348, "story": 0.00019577133907595928, "read": 0.0001945903872348706, "see": 0.00019322177995903698, "talk": 0.00018964536317087047, "show": 0.00018714909544603867, "lot": 0.00018284878405558602, "life": 0.00017104250406225948, "feel": 0.00016989466530750936, "join": 0.00015888147442008263, "do": 0.00015873015873015873, "say": 0.00013749484394335213, "try": 0.00013683634373289546, "world": 0.00012999675008124796, "make": 0.00011981787682722263, "check": 0.00011786892975011787, "week": 0.00010505305179115453, "think": 9.519276534983341e-05, "new": 8.839388314328648e-05, "thank": 8.73082855562993e-05, "night": 8.622919720617402e-05, "look": 7.396996819291368e-05, "para": 6.59152330103487e-05, "know": 6.17817867292722e-05, "love": 6.049789769805499e-05, "people": 5.2186619350798456e-05, "watch": 4.879000780640125e-05, "get": 2.6493575307987812e-05}}