{"username": "ChelseaFC", "words": {"play": 532.0, "games": 466.0, "sports": 459.0, "line": 458.0, "toy": 446.0, "stand": 422.0, "night": 421.0, "party": 376.0, "joint": 369.0, "body": 363.0, "fun": 361.0, "device": 341.0, "watches": 331.0, "football": 324.0, "vinyl": 320.0, "history": 316.0, "performance": 304.0, "practice": 297.0, "day": 292.0, "boot": 283.0, "paintball": 271.0, "work": 265.0, "baseball": 256.0, "basketball": 254.0, "business": 252.0, "club": 251.0, "court": 248.0, "fairground": 248.0, "harbor": 237.0, "fencing": 235.0, "healthcare": 232.0, "golf": 225.0, "law": 224.0, "sweeper": 221.0, "baby": 218.0, "cricket": 216.0, "dance": 214.0, "spot": 213.0, "climbing": 209.0, "game": 208.0, "aquarium": 205.0, "base": 202.0, "paddleboarding": 201.0, "wheel": 200.0, "producer": 199.0, "time": 197.0, "moving": 196.0, "event": 193.0, "promenade": 193.0, "film": 191.0, "vacation": 188.0, "gamer": 185.0, "bowling": 179.0, "tank": 178.0, "elevator": 177.0, "show": 174.0, "betting": 173.0, "labor": 171.0, "sport": 161.0, "boxing": 160.0, "sex": 157.0, "team": 157.0, "escape": 155.0, "toys": 154.0, "bartending": 152.0, "cause": 149.0, "music": 147.0, "wedding": 147.0, "cannabis": 146.0, "leader": 144.0, "nationality": 144.0, "members": 142.0, "kids": 140.0, "planning": 138.0, "tennis": 136.0, "bags": 134.0, "race": 132.0, "channel": 128.0, "living": 127.0, "sitter": 127.0, "position": 126.0, "improvement": 125.0, "control": 124.0, "self": 124.0, "season": 122.0, "product": 121.0, "internet": 117.0, "album": 115.0, "caterer": 114.0, "injury": 114.0, "men": 114.0, "soccer": 114.0, "movie": 113.0, "record": 113.0, "plastic": 112.0, "skin": 112.0, "computer": 111.0, "speakeasy": 111.0, "trailer": 111.0, "meeting": 109.0, "hub": 108.0, "family": 107.0, "home": 105.0, "youth": 104.0, "school": 103.0, "traffic": 103.0, "agency": 100.0, "course": 100.0, "hockey": 99.0, "cessation": 98.0, "shredding": 98.0, "character": 97.0, "motorsports": 97.0, "avionics": 96.0, "career": 96.0, "square": 96.0, "news": 95.0, "band": 94.0, "blog": 94.0, "children": 94.0, "theater": 94.0, "adult": 92.0, "temple": 91.0, "leasing": 90.0, "website": 90.0, "tablet": 89.0, "spring": 88.0, "preserve": 87.0, "range": 87.0, "organization": 86.0, "dealer": 85.0, "gift": 85.0, "marriage": 85.0, "cable": 84.0, "speech": 84.0, "statue": 84.0, "health": 81.0, "cream": 80.0, "care": 78.0, "concert": 78.0, "saints": 78.0, "brewery": 77.0, "project": 76.0, "technology": 76.0, "beer": 74.0, "bottled": 74.0, "drawn": 74.0, "test": 73.0, "studio": 71.0, "videographer": 71.0, "college": 69.0, "fashion": 69.0, "movies": 69.0, "research": 69.0, "information": 68.0, "arena": 67.0, "camp": 67.0, "office": 67.0, "newspaper": 66.0, "performing": 66.0, "antique": 65.0, "kebab": 64.0, "energy": 63.0, "program": 63.0, "travel": 63.0, "check": 62.0, "eye": 59.0, "eyewear": 59.0, "trail": 59.0, "foodservice": 58.0, "machine": 58.0, "phone": 58.0, "aid": 57.0, "wildlife": 57.0, "software": 56.0, "supply": 56.0, "playlist": 55.0, "rideshare": 55.0, "forces": 54.0, "production": 54.0, "racquetball": 54.0, "automation": 53.0, "economy": 53.0, "election": 53.0, "university": 53.0, "plane": 52.0, "trainer": 51.0, "writing": 50.0, "beauty": 49.0, "esports": 49.0, "gaming": 49.0, "sporting": 49.0, "furniture": 48.0, "parts": 48.0, "pitch": 48.0, "repair": 48.0, "media": 47.0, "process": 47.0, "advance": 46.0, "gifts": 46.0, "motorcycle": 46.0, "venue": 46.0, "church": 45.0, "company": 45.0, "entity": 45.0, "fraternity": 45.0, "lessons": 45.0, "sorority": 45.0, "chemical": 44.0, "bank": 43.0, "cosmetology": 43.0, "farm": 43.0, "place": 43.0, "property": 43.0, "township": 43.0, "adoption": 42.0, "education": 42.0, "extensions": 42.0, "fitness": 42.0, "glass": 42.0, "government": 42.0, "gymnastics": 42.0, "preparation": 42.0, "kitchen": 41.0, "mall": 41.0, "station": 41.0, "archery": 40.0, "assistance": 40.0, "district": 40.0, "gate": 40.0, "lab": 40.0, "marine": 40.0, "marketing": 40.0, "translator": 40.0, "vehicle": 40.0, "agriculture": 39.0, "castle": 39.0, "clothing": 39.0, "episode": 39.0, "guard": 39.0, "mining": 39.0, "pilates": 39.0, "shopping": 39.0, "art": 38.0, "fence": 38.0, "hunting": 38.0, "makeup": 38.0, "rent": 38.0, "system": 38.0, "training": 38.0, "weather": 38.0, "app": 37.0, "audiologist": 37.0, "fishing": 37.0, "design": 36.0, "door": 36.0, "driving": 36.0, "science": 36.0, "shooting": 36.0, "title": 36.0, "alcohol": 35.0, "board": 35.0, "consulting": 35.0, "diving": 35.0, "hospital": 35.0, "house": 35.0, "lodge": 35.0, "storage": 35.0, "talent": 35.0, "cabinet": 34.0, "cleaning": 34.0, "resort": 34.0, "retirement": 34.0, "service": 34.0, "palace": 33.0, "store": 33.0, "campground": 32.0, "convent": 32.0, "figure": 32.0, "protection": 32.0, "reference": 32.0, "household": 31.0, "lottery": 31.0, "marche": 31.0, "box": 30.0, "firm": 30.0, "hospitality": 30.0, "management": 30.0, "residence": 30.0, "steakhouse": 30.0, "topic": 30.0, "conditioning": 29.0, "homebrew": 29.0, "inn": 29.0, "masonry": 29.0, "meditation": 29.0, "planetarium": 29.0, "rescue": 29.0, "specialty": 29.0, "anhui": 28.0, "animation": 28.0, "apartments": 28.0, "beijing": 28.0, "computers": 28.0, "damage": 28.0, "gallery": 28.0, "skateboard": 28.0, "skating": 28.0, "soba": 28.0, "theatre": 28.0, "tianjin": 28.0, "video": 28.0, "waxing": 28.0, "xinjiang": 28.0, "apartment": 27.0, "curtains": 27.0, "investing": 27.0, "landmark": 27.0, "malpractice": 27.0, "methodist": 27.0, "counseling": 26.0, "county": 26.0, "decor": 26.0, "delivery": 26.0, "enforcement": 26.0, "pathologist": 26.0, "staging": 26.0, "television": 26.0, "duty": 25.0, "guide": 25.0, "model": 25.0, "parking": 25.0, "psychiatrist": 25.0, "saxon": 25.0, "status": 25.0, "treatment": 25.0, "weight": 25.0, "women": 25.0, "center": 24.0, "class": 24.0, "employment": 24.0, "housing": 24.0, "image": 24.0, "productions": 24.0, "state": 24.0, "agent": 23.0, "arboretum": 23.0, "campus": 23.0, "crafts": 23.0, "editor": 23.0, "freight": 23.0, "restaurant": 23.0, "rock": 23.0, "society": 23.0, "teens": 23.0, "ticket": 23.0, "alterations": 22.0, "ballroom": 22.0, "department": 22.0, "gun": 22.0, "jazz": 22.0, "photography": 22.0, "sailing": 22.0, "theme": 22.0, "chart": 21.0, "coach": 21.0, "escrow": 21.0, "hedge": 21.0, "hiking": 21.0, "immigration": 21.0, "infrastructure": 21.0, "karaoke": 21.0, "magazine": 21.0, "mission": 21.0, "passport": 21.0, "paving": 21.0, "bus": 20.0, "consignment": 20.0, "editorial": 20.0, "industry": 20.0, "interest": 20.0, "language": 20.0, "pharmaceuticals": 20.0, "signs": 20.0, "tutor": 20.0, "banner": 19.0, "circus": 19.0, "city": 19.0, "comedy": 19.0, "desert": 19.0, "distillery": 19.0, "hang": 19.0, "hospice": 19.0, "investigator": 19.0, "lodging": 19.0, "rail": 19.0, "room": 19.0, "rv": 19.0, "shoe": 19.0, "surveyor": 19.0, "wash": 19.0, "addiction": 18.0, "area": 18.0, "beach": 18.0, "development": 18.0, "light": 18.0, "railroad": 18.0, "series": 18.0, "assistant": 17.0, "assisted": 17.0, "car": 17.0, "carnival": 17.0, "fire": 17.0, "instruction": 17.0, "irani": 17.0, "island": 17.0, "ocean": 17.0, "registration": 17.0, "tiling": 17.0, "transportation": 17.0, "type": 17.0, "administrator": 16.0, "article": 16.0, "cardiologist": 16.0, "consultant": 16.0, "defense": 16.0, "endocrinologist": 16.0, "gerontologist": 16.0, "gynecologist": 16.0, "internist": 16.0, "lumber": 16.0, "marina": 16.0, "oncologist": 16.0, "outlet": 16.0, "page": 16.0, "proctologist": 16.0, "radiologist": 16.0, "region": 16.0, "solar": 16.0, "space": 16.0, "water": 16.0, "aromatherapy": 15.0, "cape": 15.0, "commerce": 15.0, "designated": 15.0, "fireplace": 15.0, "logging": 15.0, "refrigeration": 15.0, "relations": 15.0, "cleaner": 14.0, "construction": 14.0, "deck": 14.0, "exchange": 14.0, "livery": 14.0, "playground": 14.0, "printing": 14.0, "shaved": 14.0, "soul": 14.0, "testing": 14.0, "volcano": 14.0, "adige": 13.0, "detailing": 13.0, "entertainment": 13.0, "garden": 13.0, "investment": 13.0, "maternity": 13.0, "metro": 13.0, "nazarene": 13.0, "style": 13.0, "yoshoku": 13.0, "babysitter": 12.0, "batting": 12.0, "biking": 12.0, "book": 12.0, "breakfast": 12.0, "building": 12.0, "canoe": 12.0, "continent": 12.0, "convention": 12.0, "costa": 12.0, "dermatologist": 12.0, "dmv": 12.0, "electronics": 12.0, "field": 12.0, "plaza": 12.0, "recruiter": 12.0, "recycling": 12.0, "sandblasting": 12.0, "towing": 12.0, "amphitheater": 11.0, "arts": 11.0, "borough": 11.0, "cave": 11.0, "color": 11.0, "culture": 11.0, "flyboarding": 11.0, "fountain": 11.0, "genre": 11.0, "landscape": 11.0, "modeling": 11.0, "river": 11.0, "roman": 11.0, "roofing": 11.0, "safety": 11.0, "stadium": 11.0, "street": 11.0, "topics": 11.0, "trophies": 11.0, "videography": 11.0, "air": 10.0, "bail": 10.0, "basilicata": 10.0, "biotechnology": 10.0, "books": 10.0, "carpenter": 10.0, "chaat": 10.0, "credit": 10.0, "discount": 10.0, "divorce": 10.0, "doctor": 10.0, "franchise": 10.0, "fundraiser": 10.0, "heater": 10.0, "journalist": 10.0, "junkyard": 10.0, "karnataka": 10.0, "laundromat": 10.0, "molise": 10.0, "nabe": 10.0, "places": 10.0, "sightseeing": 10.0, "swimming": 10.0, "therapist": 10.0, "aviation": 9.0, "blinds": 9.0, "blues": 9.0, "dating": 9.0, "drilling": 9.0, "facility": 9.0, "forestry": 9.0, "fusion": 9.0, "jain": 9.0, "kingdom": 9.0, "mountain": 9.0, "painting": 9.0, "robotics": 9.0, "spa": 9.0, "tree": 9.0, "balloon": 8.0, "community": 8.0, "country": 8.0, "flight": 8.0, "gas": 8.0, "gastroenterologist": 8.0, "highway": 8.0, "kayak": 8.0, "kiteboarding": 8.0, "personality": 8.0, "photographer": 8.0, "pulmonologist": 8.0, "riding": 8.0, "security": 8.0, "skate": 8.0, "surgeon": 8.0, "tour": 8.0, "utility": 8.0, "waste": 8.0, "badminton": 7.0, "disability": 7.0, "henan": 7.0, "jesus": 7.0, "lingerie": 7.0, "museum": 7.0, "observatory": 7.0, "opinion": 7.0, "pier": 7.0, "prosthetics": 7.0, "province": 7.0, "satellite": 7.0, "telemarketing": 7.0, "bar": 6.0, "businesses": 6.0, "collection": 6.0, "contractor": 6.0, "cruise": 6.0, "developer": 6.0, "heliport": 6.0, "insurance": 6.0, "juvenile": 6.0, "lasik": 6.0, "luggage": 6.0, "orthopedist": 6.0, "planner": 6.0, "rodeo": 6.0, "tag": 6.0, "tex": 6.0, "trade": 6.0, "train": 6.0, "vending": 6.0, "ventilating": 6.0, "waterfall": 6.0, "aircraft": 5.0, "auditorium": 5.0, "boat": 5.0, "cabin": 5.0, "chiropractor": 5.0, "cooking": 5.0, "cosmetics": 5.0, "farmers": 5.0, "gym": 5.0, "holiness": 5.0, "homeless": 5.0, "medium": 5.0, "metal": 5.0, "monument": 5.0, "nail": 5.0, "pedicab": 5.0, "prevention": 5.0, "psychotherapist": 5.0, "recreation": 5.0, "screen": 5.0, "sculpture": 5.0, "surfing": 5.0, "teacher": 5.0, "village": 5.0, "assemblies": 4.0, "author": 4.0, "awning": 4.0, "bed": 4.0, "billiard": 4.0, "brand": 4.0, "cajun": 4.0, "carpet": 4.0, "cars": 4.0, "cemetery": 4.0, "conservation": 4.0, "cottage": 4.0, "crisis": 4.0, "designer": 4.0, "disc": 4.0, "fertility": 4.0, "grocery": 4.0, "heating": 4.0, "hostel": 4.0, "ice": 4.0, "inspector": 4.0, "landlord": 4.0, "maid": 4.0, "materials": 4.0, "merchandising": 4.0, "mirror": 4.0, "oil": 4.0, "park": 4.0, "patio": 4.0, "pawn": 4.0, "polishing": 4.0, "port": 4.0, "provider": 4.0, "seaplane": 4.0, "services": 4.0, "song": 4.0, "tax": 4.0, "tea": 4.0, "tenant": 4.0, "tinting": 4.0, "tv": 4.0, "vineyard": 4.0, "allergist": 3.0, "appliance": 3.0, "appraiser": 3.0, "bankruptcy": 3.0, "carriage": 3.0, "cart": 3.0, "casino": 3.0, "chef": 3.0, "code": 3.0, "convenience": 3.0, "counselor": 3.0, "creator": 3.0, "dentist": 3.0, "diner": 3.0, "diseases": 3.0, "dive": 3.0, "dorm": 3.0, "emissions": 3.0, "fort": 3.0, "gastronomy": 3.0, "genealogist": 3.0, "gutter": 3.0, "hobby": 3.0, "label": 3.0, "lawyer": 3.0, "litigation": 3.0, "loss": 3.0, "magazines": 3.0, "market": 3.0, "mood": 3.0, "photo": 3.0, "plumbing": 3.0, "resources": 3.0, "shop": 3.0, "steel": 3.0, "supplies": 3.0, "tattoo": 3.0, "taxi": 3.0, "union": 3.0, "writer": 3.0, "accessories": 2.0, "accountant": 2.0, "amusement": 2.0, "animal": 2.0, "bakery": 2.0, "bay": 2.0, "broker": 2.0, "brunch": 2.0, "buffet": 2.0, "builder": 2.0, "butler": 2.0, "cafeteria": 2.0, "camera": 2.0, "cartooning": 2.0, "charity": 2.0, "chicken": 2.0, "civilization": 2.0, "comfort": 2.0, "contract": 2.0, "dealership": 2.0, "dhaba": 2.0, "director": 2.0, "drug": 2.0, "drugstore": 2.0, "equipment": 2.0, "estate": 2.0, "fan": 2.0, "filipino": 2.0, "filter": 2.0, "flooring": 2.0, "gastropub": 2.0, "goods": 2.0, "grocer": 2.0, "groomer": 2.0, "ground": 2.0, "halal": 2.0, "harmonized": 2.0, "horseback": 2.0, "instructor": 2.0, "jewelry": 2.0, "jiangsu": 2.0, "laser": 2.0, "lighting": 2.0, "livestock": 2.0, "loch": 2.0, "locksmith": 2.0, "material": 2.0, "mattress": 2.0, "motor": 2.0, "nurseries": 2.0, "orthotics": 2.0, "palatine": 2.0, "picnic": 2.0, "piedmont": 2.0, "pool": 2.0, "profile": 2.0, "publisher": 2.0, "reflexologist": 2.0, "reptile": 2.0, "rink": 2.0, "shaanxi": 2.0, "siding": 2.0, "threading": 2.0, "tire": 2.0, "toilet": 2.0, "tourist": 2.0, "walker": 2.0, "winery": 2.0, "yakiniku": 2.0, "abortion": 1.0, "actor": 1.0, "aerospace": 1.0, "airline": 1.0, "airport": 1.0, "appliances": 1.0, "atm": 1.0, "auction": 1.0, "beverage": 1.0, "bicycle": 1.0, "blood": 1.0, "blower": 1.0, "breeder": 1.0, "bridge": 1.0, "broadcasting": 1.0, "burger": 1.0, "cargo": 1.0, "charter": 1.0, "christ": 1.0, "customization": 1.0, "cutting": 1.0, "dairy": 1.0, "deli": 1.0, "demolition": 1.0, "donburi": 1.0, "engineer": 1.0, "engineering": 1.0, "engraving": 1.0, "fireworks": 1.0, "food": 1.0, "garage": 1.0, "gardener": 1.0, "gardening": 1.0, "god": 1.0, "grill": 1.0, "hardware": 1.0, "hotel": 1.0, "indo": 1.0, "juice": 1.0, "lake": 1.0, "locality": 1.0, "lounge": 1.0, "medicine": 1.0, "miniature": 1.0, "monastery": 1.0, "mortgage": 1.0, "motel": 1.0, "neurologist": 1.0, "neurosurgeon": 1.0, "pest": 1.0, "petting": 1.0, "pharmacy": 1.0, "poultry": 1.0, "powder": 1.0, "rafting": 1.0, "ramen": 1.0, "resource": 1.0, "restoration": 1.0, "rose": 1.0, "sales": 1.0, "satire": 1.0, "scooter": 1.0, "shabu": 1.0, "shipping": 1.0, "snorkeling": 1.0, "spirits": 1.0, "sum": 1.0, "sunglasses": 1.0, "surgeries": 1.0, "symphony": 1.0, "tonkatsu": 1.0, "transit": 1.0, "truck": 1.0, "vitamins": 1.0, "wagashi": 1.0, "whitening": 1.0, "wig": 1.0, "wine": 1.0}, "emojis": {}, "interests": {"play": 532.0, "games": 466.0, "sports": 459.0, "line": 458.0, "toy": 446.0, "stand": 422.0, "night": 421.0, "party": 376.0, "joint": 369.0, "body": 363.0, "fun": 361.0, "device": 341.0, "watches": 331.0, "football": 324.0, "vinyl": 320.0, "history": 316.0, "performance": 304.0, "practice": 297.0, "day": 292.0, "boot": 283.0, "paintball": 271.0, "work": 265.0, "baseball": 256.0, "basketball": 254.0, "business": 252.0, "club": 251.0, "court": 248.0, "fairground": 248.0, "harbor": 237.0, "fencing": 235.0, "healthcare": 232.0, "golf": 225.0, "law": 224.0, "sweeper": 221.0, "baby": 218.0, "cricket": 216.0, "dance": 214.0, "spot": 213.0, "climbing": 209.0, "game": 208.0, "aquarium": 205.0, "base": 202.0, "paddleboarding": 201.0, "wheel": 200.0, "producer": 199.0, "time": 197.0, "moving": 196.0, "event": 193.0, "promenade": 193.0, "film": 191.0, "vacation": 188.0, "gamer": 185.0, "bowling": 179.0, "tank": 178.0, "elevator": 177.0, "show": 174.0, "betting": 173.0, "labor": 171.0, "sport": 161.0, "boxing": 160.0, "sex": 157.0, "team": 157.0, "escape": 155.0, "toys": 154.0, "bartending": 152.0, "cause": 149.0, "music": 147.0, "wedding": 147.0, "cannabis": 146.0, "leader": 144.0, "nationality": 144.0, "members": 142.0, "kids": 140.0, "planning": 138.0, "tennis": 136.0, "bags": 134.0, "race": 132.0, "channel": 128.0, "living": 127.0, "sitter": 127.0, "position": 126.0, "improvement": 125.0, "control": 124.0, "self": 124.0, "season": 122.0, "product": 121.0, "internet": 117.0, "album": 115.0, "caterer": 114.0, "injury": 114.0, "men": 114.0, "soccer": 114.0, "movie": 113.0, "record": 113.0, "plastic": 112.0, "skin": 112.0, "computer": 111.0, "speakeasy": 111.0, "trailer": 111.0, "meeting": 109.0, "hub": 108.0, "family": 107.0, "home": 105.0, "youth": 104.0, "school": 103.0, "traffic": 103.0, "agency": 100.0, "course": 100.0, "hockey": 99.0, "cessation": 98.0, "shredding": 98.0, "character": 97.0, "motorsports": 97.0, "avionics": 96.0, "career": 96.0, "square": 96.0, "news": 95.0, "band": 94.0, "blog": 94.0, "children": 94.0, "theater": 94.0, "adult": 92.0, "temple": 91.0, "leasing": 90.0, "website": 90.0, "tablet": 89.0, "spring": 88.0, "preserve": 87.0, "range": 87.0, "organization": 86.0, "dealer": 85.0, "gift": 85.0, "marriage": 85.0, "cable": 84.0, "speech": 84.0, "statue": 84.0, "health": 81.0, "cream": 80.0, "care": 78.0, "concert": 78.0, "saints": 78.0, "brewery": 77.0, "project": 76.0, "technology": 76.0, "beer": 74.0, "bottled": 74.0, "drawn": 74.0, "test": 73.0, "studio": 71.0, "videographer": 71.0, "college": 69.0, "fashion": 69.0, "movies": 69.0, "research": 69.0, "information": 68.0, "arena": 67.0, "camp": 67.0, "office": 67.0, "newspaper": 66.0, "performing": 66.0, "antique": 65.0, "kebab": 64.0, "energy": 63.0, "program": 63.0, "travel": 63.0, "check": 62.0, "eye": 59.0, "eyewear": 59.0, "trail": 59.0, "foodservice": 58.0, "machine": 58.0, "phone": 58.0, "aid": 57.0, "wildlife": 57.0, "software": 56.0, "supply": 56.0, "playlist": 55.0, "rideshare": 55.0, "forces": 54.0, "production": 54.0, "racquetball": 54.0, "automation": 53.0, "economy": 53.0, "election": 53.0, "university": 53.0, "plane": 52.0, "trainer": 51.0, "writing": 50.0, "beauty": 49.0, "esports": 49.0, "gaming": 49.0, "sporting": 49.0, "furniture": 48.0, "parts": 48.0, "pitch": 48.0, "repair": 48.0, "media": 47.0, "process": 47.0, "advance": 46.0, "gifts": 46.0, "motorcycle": 46.0, "venue": 46.0, "church": 45.0, "company": 45.0, "entity": 45.0, "fraternity": 45.0, "lessons": 45.0, "sorority": 45.0, "chemical": 44.0, "bank": 43.0, "cosmetology": 43.0, "farm": 43.0, "place": 43.0, "property": 43.0, "township": 43.0, "adoption": 42.0, "education": 42.0, "extensions": 42.0, "fitness": 42.0, "glass": 42.0, "government": 42.0, "gymnastics": 42.0, "preparation": 42.0, "kitchen": 41.0, "mall": 41.0, "station": 41.0, "archery": 40.0, "assistance": 40.0, "district": 40.0, "gate": 40.0, "lab": 40.0, "marine": 40.0, "marketing": 40.0, "translator": 40.0, "vehicle": 40.0, "agriculture": 39.0, "castle": 39.0, "clothing": 39.0, "episode": 39.0, "guard": 39.0, "mining": 39.0, "pilates": 39.0, "shopping": 39.0, "art": 38.0, "fence": 38.0, "hunting": 38.0, "makeup": 38.0, "rent": 38.0, "system": 38.0, "training": 38.0, "weather": 38.0, "app": 37.0, "audiologist": 37.0, "fishing": 37.0, "design": 36.0, "door": 36.0, "driving": 36.0, "science": 36.0, "shooting": 36.0, "title": 36.0, "alcohol": 35.0, "board": 35.0, "consulting": 35.0, "diving": 35.0, "hospital": 35.0, "house": 35.0, "lodge": 35.0, "storage": 35.0, "talent": 35.0, "cabinet": 34.0, "cleaning": 34.0, "resort": 34.0, "retirement": 34.0, "service": 34.0, "palace": 33.0, "store": 33.0, "campground": 32.0, "convent": 32.0, "figure": 32.0, "protection": 32.0, "reference": 32.0, "household": 31.0, "lottery": 31.0, "marche": 31.0, "box": 30.0, "firm": 30.0, "hospitality": 30.0, "management": 30.0, "residence": 30.0, "steakhouse": 30.0, "topic": 30.0, "conditioning": 29.0, "homebrew": 29.0, "inn": 29.0, "masonry": 29.0, "meditation": 29.0, "planetarium": 29.0, "rescue": 29.0, "specialty": 29.0, "anhui": 28.0, "animation": 28.0, "apartments": 28.0, "beijing": 28.0, "computers": 28.0, "damage": 28.0, "gallery": 28.0, "skateboard": 28.0, "skating": 28.0, "soba": 28.0, "theatre": 28.0, "tianjin": 28.0, "video": 28.0, "waxing": 28.0, "xinjiang": 28.0, "apartment": 27.0, "curtains": 27.0, "investing": 27.0, "landmark": 27.0, "malpractice": 27.0, "methodist": 27.0, "counseling": 26.0, "county": 26.0, "decor": 26.0, "delivery": 26.0, "enforcement": 26.0, "pathologist": 26.0, "staging": 26.0, "television": 26.0, "duty": 25.0, "guide": 25.0, "model": 25.0, "parking": 25.0, "psychiatrist": 25.0, "saxon": 25.0, "status": 25.0, "treatment": 25.0, "weight": 25.0, "women": 25.0, "center": 24.0, "class": 24.0, "employment": 24.0, "housing": 24.0, "image": 24.0, "productions": 24.0, "state": 24.0, "agent": 23.0, "arboretum": 23.0, "campus": 23.0, "crafts": 23.0, "editor": 23.0, "freight": 23.0, "restaurant": 23.0, "rock": 23.0, "society": 23.0, "teens": 23.0, "ticket": 23.0, "alterations": 22.0, "ballroom": 22.0, "department": 22.0, "gun": 22.0, "jazz": 22.0, "photography": 22.0, "sailing": 22.0, "theme": 22.0, "chart": 21.0, "coach": 21.0, "escrow": 21.0, "hedge": 21.0, "hiking": 21.0, "immigration": 21.0, "infrastructure": 21.0, "karaoke": 21.0, "magazine": 21.0, "mission": 21.0, "passport": 21.0, "paving": 21.0, "bus": 20.0, "consignment": 20.0, "editorial": 20.0, "industry": 20.0, "interest": 20.0, "language": 20.0, "pharmaceuticals": 20.0, "signs": 20.0, "tutor": 20.0, "banner": 19.0, "circus": 19.0, "city": 19.0, "comedy": 19.0, "desert": 19.0, "distillery": 19.0, "hang": 19.0, "hospice": 19.0, "investigator": 19.0, "lodging": 19.0, "rail": 19.0, "room": 19.0, "rv": 19.0, "shoe": 19.0, "surveyor": 19.0, "wash": 19.0, "addiction": 18.0, "area": 18.0, "beach": 18.0, "development": 18.0, "light": 18.0, "railroad": 18.0, "series": 18.0, "assistant": 17.0, "assisted": 17.0, "car": 17.0, "carnival": 17.0, "fire": 17.0, "instruction": 17.0, "irani": 17.0, "island": 17.0, "ocean": 17.0, "registration": 17.0, "tiling": 17.0, "transportation": 17.0, "type": 17.0, "administrator": 16.0, "article": 16.0, "cardiologist": 16.0, "consultant": 16.0, "defense": 16.0, "endocrinologist": 16.0, "gerontologist": 16.0, "gynecologist": 16.0, "internist": 16.0, "lumber": 16.0, "marina": 16.0, "oncologist": 16.0, "outlet": 16.0, "page": 16.0, "proctologist": 16.0, "radiologist": 16.0, "region": 16.0, "solar": 16.0, "space": 16.0, "water": 16.0, "aromatherapy": 15.0, "cape": 15.0, "commerce": 15.0, "designated": 15.0, "fireplace": 15.0, "logging": 15.0, "refrigeration": 15.0, "relations": 15.0, "cleaner": 14.0, "construction": 14.0, "deck": 14.0, "exchange": 14.0, "livery": 14.0, "playground": 14.0, "printing": 14.0, "shaved": 14.0, "soul": 14.0, "testing": 14.0, "volcano": 14.0, "adige": 13.0, "detailing": 13.0, "entertainment": 13.0, "garden": 13.0, "investment": 13.0, "maternity": 13.0, "metro": 13.0, "nazarene": 13.0, "style": 13.0, "yoshoku": 13.0, "babysitter": 12.0, "batting": 12.0, "biking": 12.0, "book": 12.0, "breakfast": 12.0, "building": 12.0, "canoe": 12.0, "continent": 12.0, "convention": 12.0, "costa": 12.0, "dermatologist": 12.0, "dmv": 12.0, "electronics": 12.0, "field": 12.0, "plaza": 12.0, "recruiter": 12.0, "recycling": 12.0, "sandblasting": 12.0, "towing": 12.0, "amphitheater": 11.0, "arts": 11.0, "borough": 11.0, "cave": 11.0, "color": 11.0, "culture": 11.0, "flyboarding": 11.0, "fountain": 11.0, "genre": 11.0, "landscape": 11.0, "modeling": 11.0, "river": 11.0, "roman": 11.0, "roofing": 11.0, "safety": 11.0, "stadium": 11.0, "street": 11.0, "topics": 11.0, "trophies": 11.0, "videography": 11.0, "air": 10.0, "bail": 10.0, "basilicata": 10.0, "biotechnology": 10.0, "books": 10.0, "carpenter": 10.0, "chaat": 10.0, "credit": 10.0, "discount": 10.0, "divorce": 10.0, "doctor": 10.0, "franchise": 10.0, "fundraiser": 10.0, "heater": 10.0, "journalist": 10.0, "junkyard": 10.0, "karnataka": 10.0, "laundromat": 10.0, "molise": 10.0, "nabe": 10.0, "places": 10.0, "sightseeing": 10.0, "swimming": 10.0, "therapist": 10.0, "aviation": 9.0, "blinds": 9.0, "blues": 9.0, "dating": 9.0, "drilling": 9.0, "facility": 9.0, "forestry": 9.0, "fusion": 9.0, "jain": 9.0, "kingdom": 9.0, "mountain": 9.0, "painting": 9.0, "robotics": 9.0, "spa": 9.0, "tree": 9.0, "balloon": 8.0, "community": 8.0, "country": 8.0, "flight": 8.0, "gas": 8.0, "gastroenterologist": 8.0, "highway": 8.0, "kayak": 8.0, "kiteboarding": 8.0, "personality": 8.0, "photographer": 8.0, "pulmonologist": 8.0, "riding": 8.0, "security": 8.0, "skate": 8.0, "surgeon": 8.0, "tour": 8.0, "utility": 8.0, "waste": 8.0, "badminton": 7.0, "disability": 7.0, "henan": 7.0, "jesus": 7.0, "lingerie": 7.0, "museum": 7.0, "observatory": 7.0, "opinion": 7.0, "pier": 7.0, "prosthetics": 7.0, "province": 7.0, "satellite": 7.0, "telemarketing": 7.0, "bar": 6.0, "businesses": 6.0, "collection": 6.0, "contractor": 6.0, "cruise": 6.0, "developer": 6.0, "heliport": 6.0, "insurance": 6.0, "juvenile": 6.0, "lasik": 6.0, "luggage": 6.0, "orthopedist": 6.0, "planner": 6.0, "rodeo": 6.0, "tag": 6.0, "tex": 6.0, "trade": 6.0, "train": 6.0, "vending": 6.0, "ventilating": 6.0, "waterfall": 6.0, "aircraft": 5.0, "auditorium": 5.0, "boat": 5.0, "cabin": 5.0, "chiropractor": 5.0, "cooking": 5.0, "cosmetics": 5.0, "farmers": 5.0, "gym": 5.0, "holiness": 5.0, "homeless": 5.0, "medium": 5.0, "metal": 5.0, "monument": 5.0, "nail": 5.0, "pedicab": 5.0, "prevention": 5.0, "psychotherapist": 5.0, "recreation": 5.0, "screen": 5.0, "sculpture": 5.0, "surfing": 5.0, "teacher": 5.0, "village": 5.0, "assemblies": 4.0, "author": 4.0, "awning": 4.0, "bed": 4.0, "billiard": 4.0, "brand": 4.0, "cajun": 4.0, "carpet": 4.0, "cars": 4.0, "cemetery": 4.0, "conservation": 4.0, "cottage": 4.0, "crisis": 4.0, "designer": 4.0, "disc": 4.0, "fertility": 4.0, "grocery": 4.0, "heating": 4.0, "hostel": 4.0, "ice": 4.0, "inspector": 4.0, "landlord": 4.0, "maid": 4.0, "materials": 4.0, "merchandising": 4.0, "mirror": 4.0, "oil": 4.0, "park": 4.0, "patio": 4.0, "pawn": 4.0, "polishing": 4.0, "port": 4.0, "provider": 4.0, "seaplane": 4.0, "services": 4.0, "song": 4.0, "tax": 4.0, "tea": 4.0, "tenant": 4.0, "tinting": 4.0, "tv": 4.0, "vineyard": 4.0, "allergist": 3.0, "appliance": 3.0, "appraiser": 3.0, "bankruptcy": 3.0, "carriage": 3.0, "cart": 3.0, "casino": 3.0, "chef": 3.0, "code": 3.0, "convenience": 3.0, "counselor": 3.0, "creator": 3.0, "dentist": 3.0, "diner": 3.0, "diseases": 3.0, "dive": 3.0, "dorm": 3.0, "emissions": 3.0, "fort": 3.0, "gastronomy": 3.0, "genealogist": 3.0, "gutter": 3.0, "hobby": 3.0, "label": 3.0, "lawyer": 3.0, "litigation": 3.0, "loss": 3.0, "magazines": 3.0, "market": 3.0, "mood": 3.0, "photo": 3.0, "plumbing": 3.0, "resources": 3.0, "shop": 3.0, "steel": 3.0, "supplies": 3.0, "tattoo": 3.0, "taxi": 3.0, "union": 3.0, "writer": 3.0, "accessories": 2.0, "accountant": 2.0, "amusement": 2.0, "animal": 2.0, "bakery": 2.0, "bay": 2.0, "broker": 2.0, "brunch": 2.0, "buffet": 2.0, "builder": 2.0, "butler": 2.0, "cafeteria": 2.0, "camera": 2.0, "cartooning": 2.0, "charity": 2.0, "chicken": 2.0, "civilization": 2.0, "comfort": 2.0, "contract": 2.0, "dealership": 2.0, "dhaba": 2.0, "director": 2.0, "drug": 2.0, "drugstore": 2.0, "equipment": 2.0, "estate": 2.0, "fan": 2.0, "filipino": 2.0, "filter": 2.0, "flooring": 2.0, "gastropub": 2.0, "goods": 2.0, "grocer": 2.0, "groomer": 2.0, "ground": 2.0, "halal": 2.0, "harmonized": 2.0, "horseback": 2.0, "instructor": 2.0, "jewelry": 2.0, "jiangsu": 2.0, "laser": 2.0, "lighting": 2.0, "livestock": 2.0, "loch": 2.0, "locksmith": 2.0, "material": 2.0, "mattress": 2.0, "motor": 2.0, "nurseries": 2.0, "orthotics": 2.0, "palatine": 2.0, "picnic": 2.0, "piedmont": 2.0, "pool": 2.0, "profile": 2.0, "publisher": 2.0, "reflexologist": 2.0, "reptile": 2.0, "rink": 2.0, "shaanxi": 2.0, "siding": 2.0, "threading": 2.0, "tire": 2.0, "toilet": 2.0, "tourist": 2.0, "walker": 2.0, "winery": 2.0, "yakiniku": 2.0, "abortion": 1.0, "actor": 1.0, "aerospace": 1.0, "airline": 1.0, "airport": 1.0, "appliances": 1.0, "atm": 1.0, "auction": 1.0, "beverage": 1.0, "bicycle": 1.0, "blood": 1.0, "blower": 1.0, "breeder": 1.0, "bridge": 1.0, "broadcasting": 1.0, "burger": 1.0, "cargo": 1.0, "charter": 1.0, "christ": 1.0, "customization": 1.0, "cutting": 1.0, "dairy": 1.0, "deli": 1.0, "demolition": 1.0, "donburi": 1.0, "engineer": 1.0, "engineering": 1.0, "engraving": 1.0, "fireworks": 1.0, "food": 1.0, "garage": 1.0, "gardener": 1.0, "gardening": 1.0, "god": 1.0, "grill": 1.0, "hardware": 1.0, "hotel": 1.0, "indo": 1.0, "juice": 1.0, "lake": 1.0, "locality": 1.0, "lounge": 1.0, "medicine": 1.0, "miniature": 1.0, "monastery": 1.0, "mortgage": 1.0, "motel": 1.0, "neurologist": 1.0, "neurosurgeon": 1.0, "pest": 1.0, "petting": 1.0, "pharmacy": 1.0, "poultry": 1.0, "powder": 1.0, "rafting": 1.0, "ramen": 1.0, "resource": 1.0, "restoration": 1.0, "rose": 1.0, "sales": 1.0, "satire": 1.0, "scooter": 1.0, "shabu": 1.0, "shipping": 1.0, "snorkeling": 1.0, "spirits": 1.0, "sum": 1.0, "sunglasses": 1.0, "surgeries": 1.0, "symphony": 1.0, "tonkatsu": 1.0, "transit": 1.0, "truck": 1.0, "vitamins": 1.0, "wagashi": 1.0, "whitening": 1.0, "wig": 1.0, "wine": 1.0}}